kraken_connector/__init__.py
kraken_connector/api/__init__.py
kraken_connector/api/account_data/__init__.py
kraken_connector/api/account_data/add_export.py
kraken_connector/api/account_data/export_status.py
kraken_connector/api/account_data/get_account_balance.py
kraken_connector/api/account_data/get_closed_orders.py
kraken_connector/api/account_data/get_extended_balance.py
kraken_connector/api/account_data/get_ledgers.py
kraken_connector/api/account_data/get_ledgers_info.py
kraken_connector/api/account_data/get_open_orders.py
kraken_connector/api/account_data/get_open_positions.py
kraken_connector/api/account_data/get_orders_info.py
kraken_connector/api/account_data/get_trade_balance.py
kraken_connector/api/account_data/get_trade_history.py
kraken_connector/api/account_data/get_trade_volume.py
kraken_connector/api/account_data/get_trades_info.py
kraken_connector/api/account_data/remove_export.py
kraken_connector/api/account_data/retrieve_export.py
kraken_connector/api/earn/__init__.py
kraken_connector/api/earn/allocate_strategy.py
kraken_connector/api/earn/deallocate_strategy.py
kraken_connector/api/earn/get_allocate_strategy_status.py
kraken_connector/api/earn/get_deallocate_strategy_status.py
kraken_connector/api/earn/list_allocations.py
kraken_connector/api/earn/list_strategies.py
kraken_connector/api/funding/__init__.py
kraken_connector/api/funding/cancel_withdrawal.py
kraken_connector/api/funding/get_deposit_addresses.py
kraken_connector/api/funding/get_deposit_methods.py
kraken_connector/api/funding/get_status_recent_deposits.py
kraken_connector/api/funding/get_status_recent_withdrawals.py
kraken_connector/api/funding/get_withdrawal_information.py
kraken_connector/api/funding/wallet_transfer.py
kraken_connector/api/funding/withdraw_funds.py
kraken_connector/api/market_data/__init__.py
kraken_connector/api/market_data/get_asset_info.py
kraken_connector/api/market_data/get_ohlc_data.py
kraken_connector/api/market_data/get_order_book.py
kraken_connector-0.0.2.dist-info/LICENSE
kraken_connector-0.0.2.dist-info/METADATA
kraken_connector-0.0.2.dist-info/WHEEL
kraken_connector-0.0.2.dist-info/RECORD
