Metadata-Version: 2.1
Name: kraken_connector
Version: 0.0.2
Summary: WS and HTTP clients for Kraken exchange API
Home-page: https://github.com/tlg7c5/kraken-connector
Author: Terry Garner
Author-email: fterrylgarner@protonmail.com
Requires-Python: >=3.8,<4.0
Classifier: Programming Language :: Python :: 3
Classifier: Programming Language :: Python :: 3.8
Classifier: Programming Language :: Python :: 3.9
Classifier: Programming Language :: Python :: 3.10
Classifier: Programming Language :: Python :: 3.11
Classifier: Programming Language :: Python :: 3.12
Requires-Dist: attrs (>=23.1.0,<24.0.0)
Requires-Dist: httpx (>=0.25.0,<0.26.0)
Requires-Dist: python-dateutil (>=2.8.2,<3.0.0)
Requires-Dist: websockets (>=12.0,<13.0)
Project-URL: Documentation, https://tlg7c5.github.io/kraken-connector/
Project-URL: Repository, https://github.com/tlg7c5/kraken-connector
